{
  "version": 1,
  "fetchedAt": "2026-06-16T11:32:09.996Z",
  "source": "https://nukaknights.com/en/",
  "axolotlOfTheMonth": {
    "month": "June 2026",
    "name": "Banded Axolotl",
    "start": "Start: 2nd Jun 2026 12:00",
    "end": "End: 7th Jul 2026 11:59",
    "timezone": "America/New_York",
    "description": [
      "Only in June in the Mire & Toxic Valley  Small Fish",
      "Axolotl & Map",
      "38%",
      "Only in June in the Mire & Toxic Valley",
      "38%",
      "Axolotl & Map",
      "Datamining: PTS Atomic Shop Items (Patch 69/70) 12th June 2026",
      "15.06.2026"
    ]
  }
}