{
  "version": 1,
  "fetchedAt": "2026-03-28T18:58:57.581Z",
  "source": "https://nukaknights.com/en/",
  "axolotlOfTheMonth": {
    "month": "March 2026",
    "name": "Clay Axolotl",
    "start": "Start: 3rd Mar 2026 12:00",
    "end": "End: 7th Apr 2026 11:59",
    "timezone": "America/New_York",
    "description": [
      "Only in March in Skyline Valley & Toxic Valley  Small Fish",
      "Axolotl & Map",
      "74%",
      "Only in March in Skyline Valley & Toxic Valley",
      "74%",
      "Axolotl & Map",
      "Atomic Shop Update 27th March 2026 Weekend Sale",
      "27.03.2026"
    ]
  }
}